jetblack_tweeter/__init__.py
jetblack_tweeter/api/__init__.py
jetblack_tweeter/api/account.py
jetblack_tweeter/api/search.py
jetblack_tweeter/api/statuses.py
jetblack_tweeter/api/stream.py
jetblack_tweeter/api/tweets.py
jetblack_tweeter/api/users.py
jetblack_tweeter/auth_client.py
jetblack_tweeter/clients/__init__.py
jetblack_tweeter/clients/aiohttp/__init__.py
jetblack_tweeter/clients/aiohttp/session.py
jetblack_tweeter/clients/bareclient/__init__.py
jetblack_tweeter/clients/bareclient/session.py
jetblack_tweeter/clients/bareclient/utils.py
jetblack_tweeter/constants.py
jetblack_tweeter/errors.py
jetblack_tweeter/py.typed
jetblack_tweeter/tweeter.py
jetblack_tweeter/types.py
jetblack_tweeter/utils.py
jetblack_tweeter-0.10.0.dist-info/WHEEL
jetblack_tweeter-0.10.0.dist-info/METADATA
jetblack_tweeter-0.10.0.dist-info/RECORD
