Metadata-Version: 2.1
Name: jetblack-tweeter
Version: 0.10.0
Summary: An asyncio twitter client
Home-page: https://github.com/rob-blackbourn/jetblack-tweeter
License: Apache-2.0
Author: Rob Blackbourn
Author-email: rob.blackbourn@gmail.com
Requires-Python: >=3.8,<4.0
Classifier: License :: OSI Approved :: Apache Software License
Classifier: Programming Language :: Python :: 3
Classifier: Programming Language :: Python :: 3.10
Classifier: Programming Language :: Python :: 3.8
Classifier: Programming Language :: Python :: 3.9
Provides-Extra: aiohttp
Provides-Extra: bareclient
Requires-Dist: aiohttp (>=3.8,<4.0); extra == "aiohttp"
Requires-Dist: bareclient (>=5.0,<6.0); extra == "bareclient"
Requires-Dist: oauthlib (>=3.1,<4.0)
Project-URL: Repository, https://github.com/rob-blackbourn/jetblack-tweeter
